{"cameraMode":{"drawMode":0,"name":"Shaded","section":"Shading Mode"},"sceneLighting":true,"audioPlay":false,"sceneViewState":{"m_AlwaysRefresh":false,"showFog":true,"showSkybox":true,"showFlares":true,"showImageEffects":true,"showParticleSystems":true,"showVisualEffectGraphs":true,"m_FxEnabled":true},"in2DMode":false,"pivot":{"x":0.0,"y":4.570000171661377,"z":0.0},"rotation":{"x":0.1878782957792282,"y":1.2370399815608835e-7,"z":-7.331396432164183e-7,"w":0.9821960926055908},"size":4.3151421546936039,"orthographic":false}